efestoclient/__init__.py
efestoclient-0.0.10.dist-info/LICENSE
efestoclient-0.0.10.dist-info/METADATA
efestoclient-0.0.10.dist-info/WHEEL
efestoclient-0.0.10.dist-info/top_level.txt
efestoclient-0.0.10.dist-info/RECORD
