Metadata-Version: 2.1
Name: efestoclient
Version: 0.0.10
Summary: EfestoClient provides controlling Efesto heat devices
Home-page: https://github.com/fredericvl/efestoclient
Author: Frederic Van Linthoudt
Author-email: frederic.van.linthoudt@gmail.com
License: UNKNOWN
Platform: UNKNOWN
Classifier: Programming Language :: Python :: 3
Classifier: License :: OSI Approved :: Apache Software License
Classifier: Operating System :: OS Independent
